BarcodeSeqKit/__init__.py
BarcodeSeqKit/_modidx.py
BarcodeSeqKit/bam_processing.py
BarcodeSeqKit/cli.py
BarcodeSeqKit/core.py
BarcodeSeqKit/fastq_processing.py
BarcodeSeqKit/sequence_utils.py
BarcodeSeqKit-0.0.4.dist-info/LICENSE
BarcodeSeqKit-0.0.4.dist-info/METADATA
BarcodeSeqKit-0.0.4.dist-info/WHEEL
BarcodeSeqKit-0.0.4.dist-info/entry_points.txt
BarcodeSeqKit-0.0.4.dist-info/top_level.txt
BarcodeSeqKit-0.0.4.dist-info/RECORD
