Metadata-Version: 2.1
Name: BarcodeSeqKit
Version: 0.0.4
Summary: BarcodeSeqKit is a library designed for extracting and processing barcoded sequences from next-generation sequencing data.
Home-page: https://github.com/mtinti/BarcodeSeqKit
Author: mtinti
Author-email: michele.tinti@gmail.com
License: Apache Software License 2.0
Keywords: nbdev jupyter notebook python
Platform: UNKNOWN
Classifier: Development Status :: 4 - Beta
Classifier: Intended Audience :: Developers
Classifier: Natural Language :: English
Classifier: Programming Language :: Python :: 3.7
Classifier: Programming Language :: Python :: 3.8
Classifier: Programming Language :: Python :: 3.9
Classifier: Programming Language :: Python :: 3.10
Classifier: Programming Language :: Python :: 3.11
Classifier: Programming Language :: Python :: 3.12
Classifier: License :: OSI Approved :: Apache Software License
Requires-Python: >=3.7
License-File: LICENSE
Requires-Dist: biopython
Requires-Dist: pandas
Requires-Dist: tqdm
Requires-Dist: fastcore
Requires-Dist: pysam
Requires-Dist: regex
Requires-Dist: pyyaml
Provides-Extra: dev
